sxyz/__init__.py
sxyz/backend.py
sxyz/config.py
sxyz/sxyz.py
sxyz/utils.py
sxyz-0.1.post1.dist-info/LICENSE
sxyz-0.1.post1.dist-info/METADATA
sxyz-0.1.post1.dist-info/WHEEL
sxyz-0.1.post1.dist-info/entry_points.txt
sxyz-0.1.post1.dist-info/top_level.txt
sxyz-0.1.post1.dist-info/RECORD
