Metadata-Version: 2.1
Name: sxyz
Version: 0.1.post1
Summary: 文件外链生成工具
Home-page: https://github.com/edgesider/sxyz
Author: edgesider
Author-email: yingkaidang@gmail.com
License: UNKNOWN
Platform: UNKNOWN
Requires-Python: >=3.5
Requires-Dist: aliyun-python-sdk-core (==2.13.10)
Requires-Dist: aliyun-python-sdk-core-v3 (==2.13.10)
Requires-Dist: aliyun-python-sdk-kms (==2.8.0)
Requires-Dist: certifi (==2019.9.11)
Requires-Dist: chardet (==3.0.4)
Requires-Dist: crcmod (==1.7)
Requires-Dist: idna (==2.8)
Requires-Dist: jmespath (==0.9.4)
Requires-Dist: oss2 (==2.8.0)
Requires-Dist: pycryptodome (==3.9.2)
Requires-Dist: qiniu (==7.2.4)
Requires-Dist: requests (==2.22.0)
Requires-Dist: urllib3 (==1.25.7)
